yc_selector/__init__.py
yc_selector-0.1.3.dist-info/LICENSE.txt
yc_selector-0.1.3.dist-info/METADATA
yc_selector-0.1.3.dist-info/WHEEL
yc_selector-0.1.3.dist-info/top_level.txt
yc_selector-0.1.3.dist-info/RECORD
